qupcrypt/WebCrypt.py
qupcrypt/__init__.py
qupcrypt/encryption.py
qupcrypt/ext.py
tests/__init__.py
tests/test_custom_aes.py
tests/test_encryption.py
tests/test_webcrypt.py
qupcrypt-0.1.6.dist-info/METADATA
qupcrypt-0.1.6.dist-info/WHEEL
qupcrypt-0.1.6.dist-info/top_level.txt
qupcrypt-0.1.6.dist-info/RECORD
